README.md
setup.py
gatling.poc.engine.egg-info/PKG-INFO
gatling.poc.engine.egg-info/SOURCES.txt
gatling.poc.engine.egg-info/dependency_links.txt
gatling.poc.engine.egg-info/requires.txt
gatling.poc.engine.egg-info/top_level.txt
poc_engine/__init__.py
poc_engine/expression.py
poc_engine/gtlog.py
poc_engine/main.py
poc_engine/proxychainwrap.sh
poc_engine/utils.py
poc_engine/thirdparty_packages/__init__.py
poc_engine/thirdparty_packages/requests/__init__.py
poc_engine/thirdparty_packages/requests/__version__.py
poc_engine/thirdparty_packages/requests/_internal_utils.py
poc_engine/thirdparty_packages/requests/adapters.py
poc_engine/thirdparty_packages/requests/api.py
poc_engine/thirdparty_packages/requests/auth.py
poc_engine/thirdparty_packages/requests/certs.py
poc_engine/thirdparty_packages/requests/compat.py
poc_engine/thirdparty_packages/requests/cookies.py
poc_engine/thirdparty_packages/requests/dump.py
poc_engine/thirdparty_packages/requests/exceptions.py
poc_engine/thirdparty_packages/requests/help.py
poc_engine/thirdparty_packages/requests/hooks.py
poc_engine/thirdparty_packages/requests/models.py
poc_engine/thirdparty_packages/requests/packages.py
poc_engine/thirdparty_packages/requests/sessions.py
poc_engine/thirdparty_packages/requests/status_codes.py
poc_engine/thirdparty_packages/requests/structures.py
poc_engine/thirdparty_packages/requests/utils.py