Metadata-Version: 2.1
Name: gatling.poc.engine
Version: 0.7.2
Summary: yml poc parser sdk for gatling
Home-page: UNKNOWN
Author: 
Author-email: 
License: UNKNOWN
Platform: UNKNOWN
Classifier: Programming Language :: Python :: 3
Requires-Python: >=3.6
